LICENCE.txt
README.md
pyproject.toml
src/sockcopy/__init__.py
src/sockcopy.egg-info/PKG-INFO
src/sockcopy.egg-info/SOURCES.txt
src/sockcopy.egg-info/dependency_links.txt
src/sockcopy.egg-info/top_level.txt